monitor/__init__.py
monitor/logs.py
monitor/scripts.py
monitor/config/__init__.py
monitor/config/apache_exporter_err.mtail
monitor/config/filewave_django.mtail
monitor/config/fwldap.mtail
monitor/config/monitor-v13.conf
monitor/config/postgres.mtail
monitor/config/prometheus.yml
filewave_monitor_v13-1.0.5.dist-info/LICENSE
filewave_monitor_v13-1.0.5.dist-info/METADATA
filewave_monitor_v13-1.0.5.dist-info/WHEEL
filewave_monitor_v13-1.0.5.dist-info/entry_points.txt
filewave_monitor_v13-1.0.5.dist-info/top_level.txt
filewave_monitor_v13-1.0.5.dist-info/RECORD
