Metadata-Version: 2.1
Name: filewave-monitor-v13
Version: 1.0.5
Summary: An additional module that installs programs/config required to monitor v13 instances via Prometheus.
Home-page: https://github.com/johncclayton/monitor-fw-13
Author: John Clayton
Author-email: johnc@filewave.com
License: UNKNOWN
Platform: UNKNOWN
Classifier: Programming Language :: Python :: 3
Classifier: License :: OSI Approved :: MIT License
Classifier: Operating System :: OS Independent
Requires-Python: >=3.6
Requires-Dist: click
Requires-Dist: progressbar2
